sls_env_yml_parser/__init__.py
sls_env_yml_parser/yml_parser.py
serverless_env_yml_parser-0.0.1.dist-info/LICENSE.txt
serverless_env_yml_parser-0.0.1.dist-info/METADATA
serverless_env_yml_parser-0.0.1.dist-info/WHEEL
serverless_env_yml_parser-0.0.1.dist-info/top_level.txt
serverless_env_yml_parser-0.0.1.dist-info/RECORD
