Metadata-Version: 2.1
Name: serverless-env-yml-parser
Version: 0.0.1
Summary: A package to extract environmental variables from serverless.env.yml for local development
Home-page: https://github.com/endrus/sls-env-yml-parser
Author: Andrei Khrapavitski
Author-email: andrei.khrapavitski@gmail.com
License: MIT
Project-URL: Documentation, https://github.com/endrus/sls-env-yml-parser
Keywords: serverless,sls,serverless.env.yml
Platform: UNKNOWN
Classifier: Development Status :: 3 - Alpha
Classifier: License :: OSI Approved :: MIT License
Classifier: Programming Language :: Python :: 3.6
Classifier: Programming Language :: Python :: 3.7
Requires-Python: >=3.6
